{
  "latestVersionCode": 89,
  "latestVersionName": "1.0.89",
  "required": false,
  "title": "تحديث حسابي التجاري 1.0.86-1.0.89",
  "message": "حزمة الفحص النهائي قبل المرشح للنشر: فحص نسخة APK، مرشح النشر، تشخيص كتالوج العميل، ومراجعة بيانات السداد وكشف الحساب بدون تغيير منطق Firestore أو العمليات الحساسة.",
  "apkUrl": "https://github.com/attef7474-byte/hesabi-app/releases/latest/download/hesabi-app-latest.apk",
  "releaseNotes": "إضافة modules: 25_apk_version_final_check.js, 26_production_release_candidate.js, 27_customer_catalog_bug_fixes.js, 28_payments_statements_real_data.js، مع تحديث الفحص الشامل ليطابق 1.0.89 / build 89.",
  "notes": "حزمة تثبيت آمنة مجمعة من 1.0.86 إلى 1.0.89.",
  "versionName": "1.0.89",
  "versionCode": 89,
  "minimumSupportedVersionCode": 60,
  "forceRefresh": true
}